binlite/__init__.py
binlite/accretion.py
binlite/constants.py
binlite/flux.py
binlite/data/q1_MdotP_RetroL2_Discoe0p8_NFourier30_sigma10P_Nt1000_makeccInput.dat
binlite/data/q1_MdotP_progL1_NFourier60_sigma10P_Nt1000_makeccInput.dat
binlite/data/q1_MdotP_progL5_NFourier60_sigma10P_Nt1000_makeccInput.dat
binlite/data/q1_MdotS_RetroL2_Discoe0p8_NFourier30_sigma10P_Nt1000_makeccInput.dat
binlite/data/q1_MdotS_progL1_NFourier60_sigma10P_Nt1000_makeccInput.dat
binlite/data/q1_MdotS_progL5_NFourier60_sigma10P_Nt1000_makeccInput.dat
binlite/data/q1_MdotTot_RetroL2_Discoe0p8_NFourier30_sigma10P_Nt1000_makeccInput.dat
binlite/data/q1_MdotTot_progL1_NFourier60_sigma10P_Nt1000_makeccInput.dat
binlite/data/q1_MdotTot_progL5_NFourier60_sigma10P_Nt1000_makeccInput.dat
binlite-1.1.1.dist-info/LICENSE.md
binlite-1.1.1.dist-info/METADATA
binlite-1.1.1.dist-info/WHEEL
binlite-1.1.1.dist-info/top_level.txt
binlite-1.1.1.dist-info/RECORD
