Metadata-Version: 2.1
Name: binlite
Version: 1.1.1
Summary: Rapidly generate periodic lightcurves of accreting binaries
Home-page: https://github.com/nbia-gwastro/binlite
Author: Christopher Tiede & Daniel D'Orazio
Author-email: 22056557+ctiede@users.noreply.github.com
Maintainer: Christopher Tiede & Daniel D'Orazio
License: MIT
Platform: Any
License-File: LICENSE.md
Requires-Dist: setuptools
Requires-Dist: numpy
Requires-Dist: scipy
